awdb/__init__.py
awdb/cli.py
awdb/exceptions.py
awdb/serializer.py
awdb/trace.py
awdb/utils.py
awdb/cli/__init__.py
awdb/cli/client.py
awdb/cli/commands.py
awdb/cli/server.py
awdb-0.0.24.dist-info/METADATA
awdb-0.0.24.dist-info/WHEEL
awdb-0.0.24.dist-info/entry_points.txt
awdb-0.0.24.dist-info/top_level.txt
awdb-0.0.24.dist-info/RECORD
