Metadata-Version: 2.1
Name: awdb
Version: 0.0.24
Summary: WebSocket Debugger
Home-page: https://github.com/archeti-org/awdb.git
Author: Archeti
Author-email: info@archeti.ca
License: UNKNOWN
Platform: UNKNOWN
Classifier: Programming Language :: Python :: 3
Classifier: License :: OSI Approved :: MIT License
Classifier: Operating System :: OS Independent
Requires-Python: >=3.6
Requires-Dist: aioconsole
Requires-Dist: aiohttp (>=3.4)
Requires-Dist: multidict (>=4.1.0)
